polyjit/__init__.py
polyjit/experiments/__init__.py
polyjit/experiments/compilestats.py
polyjit/experiments/ijpp.py
polyjit/experiments/mse.py
polyjit/experiments/papi.py
polyjit/experiments/pgo.py
polyjit/experiments/pj_collect.py
polyjit/experiments/pj_cs.py
polyjit/experiments/pj_likwid.py
polyjit/experiments/pj_papi.py
polyjit/experiments/pj_perf.py
polyjit/experiments/pj_raw.py
polyjit/experiments/pj_sequence.py
polyjit/experiments/pjtest.py
polyjit/experiments/pollytest.py
polyjit/experiments/polyjit.py
polyjit/experiments/profileScopDetection.py
polyjit/experiments/polly/__init__.py
polyjit/experiments/polly/openmp.py
polyjit/experiments/polly/openmpvect.py
polyjit/experiments/polly/polly.py
polyjit/experiments/polly/pollyperformance.py
polyjit/experiments/polly/vectorize.py
polyjit/reports/__init__.py
polyjit/reports/compilestats.py
polyjit.experiments-3.3.0.dist-info/METADATA
polyjit.experiments-3.3.0.dist-info/RECORD
polyjit.experiments-3.3.0.dist-info/WHEEL
polyjit.experiments-3.3.0.dist-info/top_level.txt
