Metadata-Version: 2.1
Name: polyjit.experiments
Version: 3.3.0
Summary: Additional experiments used by PolyJIT with BenchBuild.
Home-page: https://github.com/PolyJIT/polyjit.experiments
Author: Andreas Simbuerger
Author-email: simbuerg@fim.uni-passau.de
License: MIT
Keywords: benchbuild experiments
Platform: UNKNOWN
Classifier: Development Status :: 4 - Beta
Classifier: Intended Audience :: Developers
Classifier: Topic :: Software Development :: Testing
Classifier: License :: OSI Approved :: MIT License
Classifier: Programming Language :: Python :: 3
Requires-Dist: benchbuild (>=3.3.0)
